awscfncli2/__init__.py
awscfncli2/__main__.py
awscfncli2/cli/__init__.py
awscfncli2/cli/autocomplete.py
awscfncli2/cli/context.py
awscfncli2/cli/main.py
awscfncli2/cli/monkeypatch_clickcompletion.py
awscfncli2/cli/multicommand.py
awscfncli2/cli/commands/__init__.py
awscfncli2/cli/commands/drift/__init__.py
awscfncli2/cli/commands/drift/drift.py
awscfncli2/cli/commands/drift/detect/__init__.py
awscfncli2/cli/commands/drift/detect/detect.py
awscfncli2/cli/commands/drift/diff/__init__.py
awscfncli2/cli/commands/drift/diff/diff.py
awscfncli2/cli/commands/generate/__init__.py
awscfncli2/cli/commands/generate/generate.py
awscfncli2/cli/commands/stack/__init__.py
awscfncli2/cli/commands/stack/stack.py
awscfncli2/cli/commands/stack/cancel/__init__.py
awscfncli2/cli/commands/stack/cancel/cancel.py
awscfncli2/cli/commands/stack/delete/__init__.py
awscfncli2/cli/commands/stack/delete/delete.py
awscfncli2/cli/commands/stack/deploy/__init__.py
awscfncli2/cli/commands/stack/deploy/deploy.py
awscfncli2/cli/commands/stack/describe/__init__.py
awscfncli2/cli/commands/stack/describe/describe.py
awscfncli2/cli/commands/stack/sync/__init__.py
awscfncli2/cli/commands/stack/sync/sync.py
awscfncli2/cli/commands/stack/tail/__init__.py
awscfncli2/cli/commands/stack/tail/tail.py
awscfncli2/cli/commands/stack/update/__init__.py
awscfncli2/cli/commands/stack/update/update.py
awscfncli2/cli/commands/status/__init__.py
awscfncli2/cli/commands/status/status.py
awscfncli2/cli/commands/validate/__init__.py
awscfncli2/cli/commands/validate/validate.py
awscfncli2/cli/utils/__init__.py
awscfncli2/cli/utils/colormaps.py
awscfncli2/cli/utils/common.py
awscfncli2/cli/utils/deco.py
awscfncli2/cli/utils/events.py
awscfncli2/cli/utils/pager.py
awscfncli2/cli/utils/pprint.py
awscfncli2/config/__init__.py
awscfncli2/config/annotated-sample-config.yaml
awscfncli2/config/config.py
awscfncli2/config/deployment.py
awscfncli2/config/formats.py
awscfncli2/config/sample-config.yaml
awscfncli2/config/schema.py
awscfncli2-3.1.1.dist-info/AUTHORS
awscfncli2-3.1.1.dist-info/LICENSE
awscfncli2-3.1.1.dist-info/METADATA
awscfncli2-3.1.1.dist-info/WHEEL
awscfncli2-3.1.1.dist-info/entry_points.txt
awscfncli2-3.1.1.dist-info/top_level.txt
awscfncli2-3.1.1.dist-info/RECORD
