Metadata-Version: 2.1
Name: awscfncli2
Version: 3.1.1
Summary: AWS CloudFormation CLI
Home-page: https://github.com/Kotaimen/awscfncli
Author: Kotaimen, Ray
Author-email: kotaimen.c@gmail.com, gliese.q@gmail.com
License: MIT
Keywords: aws cfn cli awscfncli cloudformation changeset sam serverless
Platform: UNKNOWN
Classifier: Development Status :: 5 - Production/Stable
Classifier: Environment :: Console
Classifier: Programming Language :: Python :: 3.7
Classifier: Programming Language :: Python :: 3.8
Classifier: Programming Language :: Python :: 3.9
Classifier: License :: OSI Approved :: MIT License
Classifier: Intended Audience :: Developers
Classifier: Intended Audience :: System Administrators
Classifier: Topic :: Internet
Classifier: Topic :: Software Development :: Build Tools
Classifier: Topic :: Utilities
Requires-Python: >=3.7
License-File: LICENSE
License-File: AUTHORS
Requires-Dist: botocore (<2,>=1.17)
Requires-Dist: boto3 (<2,>=1.14)
Requires-Dist: awscli (<2,>=1.18)
Requires-Dist: click (<8,>=7.0)
Requires-Dist: click-completion (==0.5.2)
Requires-Dist: PyYAML (<6,>=5)
Requires-Dist: jsonschema (<6,>=3)
Requires-Dist: backoff (<2,>=1.10.0)
